LICENSE
README.md
setup.cfg
setup.py
gMCSpy/MinimalCutSetClass.py
gMCSpy/OptimizationProblem.py
gMCSpy/ProblemDefinitions.py
gMCSpy/ProblemInterpreters.py
gMCSpy/Utilities.py
gMCSpy/Validations.py
gMCSpy/__init__.py
gMCSpy/calculateGMCS.py
gMCSpy/calculateMCS.py
gMCSpy/calculateReadjustment.py
gMCSpy/calculateSyntheticDosageGMCS.py
gMCSpy.egg-info/PKG-INFO
gMCSpy.egg-info/SOURCES.txt
gMCSpy.egg-info/dependency_links.txt
gMCSpy.egg-info/requires.txt
gMCSpy.egg-info/top_level.txt
test/tests_ProblemDefinitions.py